<?xml version="1.0" encoding="utf-8"?>
<year year="0" >
    <day day="0" type="int">
        <class id ="0">
            <name>Materiali per l'ing Elettrica</name>
            <teacher>ACCIANI Giuseppe</teacher>
            <room>8</room>
            <start_time>08.30</start_time>
            <end_time>11.00</end_time>
        </class>
        <class id ="1">
            <name>Reti elettriche</name>
            <teacher>CARNIMEO Leonarda</teacher>
            <room>8</room>
            <start_time>11.00</start_time>
            <end_time>13.30</end_time>
        </class>
        <class id ="2">
            <name>Illuminazione artificiale</name>
            <teacher>CAVONE Giuseppe</teacher>
            <room>24</room>
            <start_time>14.00</start_time>
            <end_time>16.30</end_time>
        </class>
    </day>

    <day day="1">
        <class id ="0">
            <name>Macchine ed Energetica</name>
            <teacher>TORRESI Marco</teacher>
            <room>24</room>
            <start_time>08.30</start_time>
            <end_time>11.00</end_time>
        </class>
        <class id ="1">
            <name>Reti elettriche</name>
            <teacher>CARNIMEO Leonarda</teacher>
            <room>4</room>
            <start_time>11.00</start_time>
            <end_time>13.30</end_time>
        </class>
        <class id ="2">
            <name>Controllo digitale</name>
            <teacher>MAIONE Guido</teacher>
            <room>21</room>
            <start_time>14.00</start_time>
            <end_time>16.30</end_time>
        </class>
        <class id ="3">
            <name>Illuminazione artificiale</name>
            <teacher>CAVONE Giuseppe</teacher>
            <room>21</room>
            <start_time>16.30</start_time>
            <end_time>19.00</end_time>
        </class>
    </day>

    <day day="2">
        <class id ="0">
            <name>Macchine ed Energetica</name>
            <teacher>TORRESI Marco</teacher>
            <room>13</room>
            <start_time>08.30</start_time>
            <end_time>11.00</end_time>
        </class>
        <class id ="1">
            <name>Reti elettriche</name>
            <teacher>CARNIMEO Leonarda</teacher>
            <room>6</room>
            <start_time>11.00</start_time>
            <end_time>13.30</end_time>
        </class>
        <class id ="2">
            <name>Dynamical Systems Theory </name>
            <teacher>DOTOLI Mariagrazia</teacher>
            <room>12</room>
            <start_time>14.00</start_time>
            <end_time>16.30</end_time>
        </class>
    </day>
    <day day="3">
        <class id ="0">
            <name>Dynamical Systems Theory </name>
            <teacher>DOTOLI Mariagrazia</teacher>
            <room>12</room>
            <start_time>08.30</start_time>
            <end_time>11.00</end_time>
        </class>
        <class id ="1">
            <name>Gest. Intel. Impianti Elettrici</name>
            <teacher>BRONZINI Marco</teacher>
            <room>8</room>
            <start_time>11.00</start_time>
            <end_time>13.30</end_time>
        </class>
        <class id ="2">
            <name>null</name>
            <start_time>14.00</start_time>
            <end_time>16.30</end_time>
        </class>
        <class id ="3">
            <name>Materiali per l'ing Elettrica</name>
            <teacher>ACCIANI Giuseppe</teacher>
            <room>4</room>
            <start_time>16.30</start_time>
            <end_time>19.00</end_time>
        </class>
    </day>

    <day day="4">
        <class id ="0">
            <name>Controllo digitale</name>
            <teacher>MAIONE Guido</teacher>
            <room>26</room>
            <start_time>08.30</start_time>
            <end_time>11.00</end_time>
        </class>
        <class id ="1">
            <name>Reti elettriche</name>
            <teacher>CARNIMEO Leonarda</teacher>
            <room>11</room>
            <start_time>11.00</start_time>
            <end_time>13.30</end_time>
        </class>
        <class id ="2">
            <name>Gest. Intel. Impianti Elettrici</name>
            <teacher>BRONZINI Marco</teacher>
            <room>8</room>
            <start_time>14.00</start_time>
            <end_time>16.30</end_time>
        </class>
    </day>
</year>